coleridge/__init__.py
coleridge/coleridge.py
coleridge/cronfun.py
coleridge/decorated.py
coleridge/decorator.py
coleridge/get_types.py
coleridge/models/__init__.py
coleridge/models/connection.py
coleridge/models/empty.py
coleridge/models/response.py
coleridge/models/value.py
coleridge/rabbit.py
coleridge/result.py
coleridge-0.1.1.dist-info/LICENSE
coleridge-0.1.1.dist-info/METADATA
coleridge-0.1.1.dist-info/WHEEL
coleridge-0.1.1.dist-info/RECORD
